Metadata-Version: 1.0
Name: alex-message-server
Version: 0.8.0
Summary: alex_message_server
Home-page: UNKNOWN
Author: Alexey V. Danilyuk
Author-email: danilyuk-aleksey@mail.ru
License: UNKNOWN
Platform: UNKNOWN
